mach3
