Metadata-Version: 1.2
Name: mach3
Version: 0.3.1
Summary: Recursively parse and index subtitle text for future use.
Home-page: https://github.com/Calvin-Xu/mach3-cli
Author: Pinlin Xu
Author-email: calvinxu806@gmail.com
License: MIT
Download-URL: https://github.com/Calvin-Xu/mach3-cli/archive/0.1.tar.gz
Platform: any
Classifier: Development Status :: 5 - Production/Stable
Classifier: Environment :: Console
Classifier: Intended Audience :: Developers
Classifier: Operating System :: POSIX
Classifier: Operating System :: MacOS
Classifier: Operating System :: Unix
Classifier: Operating System :: Microsoft :: Windows
Classifier: Programming Language :: Python
Classifier: Programming Language :: Python :: 3
Classifier: Topic :: Software Development :: Libraries :: Python Modules
Requires-Python: >=3
